[
{"group":"ALTER","comment":"#ALTERTOTO#KURUSIN25*21*09*86"},
{"group":"Hoho","comment":"KAOSBOLONG : 58*41*36 #HOHOTOGEL"},
{"group":"KAPAL","comment":"#KAPALSLOT ( KERUMUNAN ) = 35*52*02"},
{"group":"RIATOTO","comment":"#RIATOTO KOLOMBOLONG = 15*03*64"},
{"group":"PEDRO","comment":"#PEDRO4D (KOLANGBALING*56*14*46)"},
{"group":"DIVA4D","comment":"#DIVA4D (KUNDURUNDUR3) = 44*13*50"},
{"group":"EYANG","comment":"#EYANGSLOT 68*72 ( KOMOROTOM )"},
{"group":"BLITAR","comment":"#BLITAR4D (KILATPETIR) = 19*12"},
{"group":"LOGAM","comment":"#LOGAMTOTO=KIRIKKRIK21= 97*10#"},
{"group":"TEST1","comment":"Leko"},
{"group":"TEST2","comment":"Nemo"},
{"group":"TEST3","comment":"Tiam"},
{"group":"TEST4","comment":"Telo"},
{"group":"TEST5","comment":"Bandu"},
{"group":"TEST6","comment":",Bafu"},
{"group":"TEST7","comment":"babus"},
{"group":"TEST8","comment":"Babu"}
]