[
{"group":"ALTER","comment":"#ALTERTOTO#PAKUKUTARA*68*95*52"},
{"group":"Hoho","comment":"PARLENTE : 25*73*79 #HOHOTOGEL"},
{"group":"KAPAL","comment":"#KAPALSLOT ( PAKUAN28 ) = 98*66*40"},
{"group":"RIATOTO","comment":"#RIATOTO PIMPINAN = 20*03*63"},
{"group":"PEDRO","comment":"#PEDRO4D (PURARA23*81*14*08)"},
{"group":"DIVA4D","comment":"#DIVA4D (PAPIPU56) = 89*36*47"},
{"group":"EYANG","comment":"#EYANGSLOT 30*33 ( PEMBODONG )"},
{"group":"BLITAR","comment":"#BLITAR4D (PELANGI77) = 61*41"},
{"group":"LOGAM","comment":"#LOGAMTOTO=PELANGAIR= 32*37#"},
{"group":"TEST1","comment":"Leko"},
{"group":"TEST2","comment":"Nemo"},
{"group":"TEST3","comment":"Tiam"},
{"group":"TEST4","comment":"Telo"},
{"group":"TEST5","comment":"Bandu"},
{"group":"TEST6","comment":",Bafu"},
{"group":"TEST7","comment":"babus"},
{"group":"TEST8","comment":"Babu"}
]