[
{"group":"UPINSLOT","comment":"#UPINSLOT ( QONCCER88 ) 59*50*30 BETTING"},
{"group":"K86T","comment":"K86TOTO ( QQCHERY88 ) : 67*49*28"},
{"group":"TOYIBSLOT","comment":"#TOYIBSLOT ( QERBAU04 ) : 85*31*63"},
{"group":"TAFSIR","comment":"SIJITOGEL QUANTUM33 72*05*85"},
{"group":"PULKAMT0T0","comment":"PULKAM (QOALA3) 31*53*22"},
{"group":"ALLPAS","comment":"Tok99Toto ( QWERTYY28 ) : 65*26*24"},
{"group":"LOGAMTOTO","comment":"#LOGAMTOTO=QWANDU66= 63*34#"},
{"group":"RIATOTO","comment":"#RIATOTO quartz8 = 77*43*93"},
{"group":"DIVA4D","comment":"#DIVA4D (QWANDU66) = 79*89*10"},
{"group":"KAPALSLOT","comment":"#KAPALSLOT ( QUICKLY33 ) = 82*68*61"},
{"group":"BLITAR","comment":"#BLITAR4D (QOPILU09) = 44*03"},
{"group":"KOITOTO","comment":"#KOITOTO ( QUARTER ) 88*46#10"},
{"group":"LING","comment":"LING77 (QONCCER88) 67*49"},
{"group":"KKKKKKK","comment":"LING77 (aaaaaaa) 1.1.1"},
{"group":"KKKKKKK","comment":"LING77 (aaaaaaa) 1.1.1"},
{"group":"KKKKKKK","comment":"LING77 (aaaaaaa) 1.1.1"},
{"group":"KKKKKKK","comment":"LING77 (aaaaaaa) 1.1.1"}
]