[
{"group":"ALLPAS","comment":"Tok99Toto ( EJIAN77 ) : 78*56*22"},
{"group":"BUKU","comment":"IYATOTO SELOKAN48 16*51*67"},
{"group":"TIKTAK","comment":"Tiktaktogel / SENDANG49 / 12 , 96 , 62"},
{"group":"TAFSIR MIMPI","comment":"SIJITOGEL ERAT88 97*41*23"},
{"group":"KEI","comment":"#keitogel = (SEMPRUL28) = 98*76*11"},
{"group":"LAHAN","comment":"#KIATOTO(SINTING84)*75*18"},
{"group":"453P VIP","comment":"ASEPTOGEL SEMBUR68 26*17*09"},
{"group":"UPIN","comment":"#UPINSLOT ( ERANG20 ) 08*15*10 BETTING"},
{"group":"PULKAM","comment":"#PULKAMTOTO (ENGGAN18) : 94*53*99"},
{"group":"JNE","comment":"#JNETOTO(SENENG80)*72*81*99"},
{"group":"TOYIB","comment":"#TOYIBSLOT ( SANGGAR81 ) : 19*49*02"},
{"group":"MASTER KUY","comment":"TOGELKUY SARUNG82 63*70*21"},
{"group":"KOI","comment":"#KOITOTO ( SEMPAKK83 ) 28*59"},
{"group":"K86","comment":"K86TOTO ( ENTOK11 ) : 39*07*38"},
{"group":"VESPA","comment":"VESPATOGEL (SEMBILU85) 32*57*36"},
{"group":"NEMO","comment":"NEMO4D (SEKIAN86) : 73*47*29"},
{"group":"KIKO","comment":"#KIKOTOTO (SERDADU87) = 27*44"}
]