[
{"group":"ALLPAS","comment":"Tok99Toto ( FERMEN59 ) : 46*20*02"},
{"group":"BUKU","comment":"IYATOTO KENTER52 05*30*09"},
{"group":"TIKTAK","comment":"Tiktaktogel / KEMPLUNG53 / 12 , 80 , 11"},
{"group":"TAFSIR MIMPI","comment":"SIJITOGEL FERDA60 01*32*39"},
{"group":"KEI","comment":"#keitogel = (KANGKUNG55) = 36*43*94"},
{"group":"LAHAN","comment":"#KIATOTO(KAMBING64)*92*22"},
{"group":"453P VIP","comment":"ASEPTOGEL KALUNG57 45*54*17"},
{"group":"UPIN","comment":"#UPINSLOT ( FINAL64 ) 67*26*00 BETTING"},
{"group":"PREDIKSI","comment":"MAJAPAHIT4D #FASIK62 :: 81*88*33"},
{"group":"JNE","comment":"#JNETOTO(KUMBANG60)*99*90*33"},
{"group":"TOYIB","comment":"#TOYIBSLOT ( KOLONG61 ) : 48*91*76"},
{"group":"MASTER KUY","comment":"TOGELKUY KODOK62 71*49*84"},
{"group":"KOI","comment":"#KOITOTO ( KUSAM67 ) 70*14"},
{"group":"K86","comment":"K86TOTO ( FORMULA52 ) : 85*69*35"},
{"group":"VESPA","comment":"VESPATOGEL (KEMBAR65) 89*24*40"},
{"group":"NEMO","comment":"NEMO4D (KADAR66) : 51*29*95"},
{"group":"KIKO","comment":"#KIKOTOTO (KESELEK63 ) = 82*83"}
]