[
{"group":"ALLPAS","comment":"Tok99Toto ( CAKADUR14 ) : 30*09*75"},
{"group":"BUKU","comment":"IYATOTO CAKTRAS 96*24*03"},
{"group":"TIKTAK","comment":"Tiktaktogel / CASAN36 / 00 , 72 , 77"},
{"group":"TAFSIR MIMPI","comment":"SIJITOGEL CALKON26 48*22*66"},
{"group":"KEI","comment":"#keitogel = (CIMN26) = 69*06*41"},
{"group":"LAHAN","comment":"#KIATOTO(CIMAR19)*59*26"},
{"group":"453P VIP","comment":"ASEPTOGEL CAKADUR14 60*36*65"},
{"group":"UPIN","comment":"#UPINSLOT ( CUMNI21 ) 18*20*17 BETTING"},
{"group":"PULKAM","comment":"#PULKAMTOTO (CUMNI212) : 18*20*17"},
{"group":"JNE","comment":"#JNETOTO(CAKUDIR19)*60*36*65"},
{"group":"TOYIB","comment":"#TOYIBSLOT ( CUMNI212 ) : 59*26*93"},
{"group":"MASTER KUY","comment":"TOGELKUY CIRUN19 69*06*93"},
{"group":"KOI","comment":"#KOITOTO ( CUMNI21 ) 48*22"},
{"group":"K86","comment":"K86TOTO ( CAKTRAS ) : 00*72*77"},
{"group":"VESPA","comment":"VESPATOGEL (CAHMBUH) 96*24*03"},
{"group":"NEMO","comment":"NEMO4D (CAKUDIR19) : 30*09*75"},
{"group":"KIKO","comment":"#KIKOTOTO (CAHAKBAR) = 41*68"}
]