[
{"group":"ALLPAS","comment":"Tok99Toto ( CAKADUR14 ) : 00*79*45"},
{"group":"BUKU","comment":"IYATOTO CAKTRAS 66*94*73"},
{"group":"TIKTAK","comment":"Tiktaktogel / CASAN36 / 70 , 42 , 47"},
{"group":"TAFSIR MIMPI","comment":"SIJITOGEL CALKON26 18*92*36"},
{"group":"KEI","comment":"#keitogel = (CIMN26) = 39*76*11"},
{"group":"LAHAN","comment":"#KIATOTO(CIMAR19)*29*96"},
{"group":"453P VIP","comment":"ASEPTOGEL CAKADUR14 30*06*35"},
{"group":"UPIN","comment":"#UPINSLOT ( CUMNI21 ) 88*90*87 BETTING"},
{"group":"PULKAM","comment":"#PULKAMTOTO (CUMNI212) : 88*90*87"},
{"group":"JNE","comment":"#JNETOTO(CAKUDIR19)*30*06*35"},
{"group":"TOYIB","comment":"#TOYIBSLOT ( CUMNI212 ) : 29*96*63"},
{"group":"MASTER KUY","comment":"TOGELKUY CIRUN19 39*76*63"},
{"group":"KOI","comment":"#KOITOTO ( CUMNI21 ) 18*92"},
{"group":"K86","comment":"K86TOTO ( CAKTRAS ) : 70*42*47"},
{"group":"VESPA","comment":"VESPATOGEL (CAHMBUH) 66*94*73"},
{"group":"NEMO","comment":"NEMO4D (CAKUDIR19) : 00*79*45"},
{"group":"KIKO","comment":"#KIKOTOTO (CAHAKBAR) = 11*38"}
]