[
{"group":"ALLPAS","comment":"Tok99Toto ( MELONGOBEGOK ) : 85*22*57"},
{"group":"BUKU","comment":"IYATOTO MANDINI28 75*42*09"},
{"group":"TIKTAK","comment":"Tiktaktogel / MASKURAWAN / 76 , 52 , 09"},
{"group":"TAFSIR MIMPI","comment":"SIJITOGEL MANAHIWAK 34*36*33"},
{"group":"KEI","comment":"#keitogel = (MUBENGAN52) = 46*25*91"},
{"group":"LAHAN","comment":"#KIATOTO(MANCURMUJUR)*12*40"},
{"group":"453P VIP","comment":"ASEPTOGEL MULETENAK 16*88*93"},
{"group":"UPIN","comment":"#UPINSLOT ( MENDUNGKUL ) 64*38*82 BETTING"},
{"group":"PREDIKSI","comment":"MAJAPAHIT4D #MEKASIH92 :: 43*56*71"},
{"group":"JNE","comment":"#JNETOTO(MANOKNURI)*06*01*41"},
{"group":"TOYIB","comment":"#TOYIBSLOT ( MEKASIH92 ) : 20*99*65"},
{"group":"MASTER KUY","comment":"TOGELKUY MENCLOKCUK 03*05*35"},
{"group":"KOI","comment":"#KOITOTO ( MENDUNGKUL ) 86*94"},
{"group":"K86","comment":"K86TOTO ( MANDINI28 ) : 51*39*44"},
{"group":"VESPA","comment":"VESPATOGEL (MARISUWEK) 37*28*97"},
{"group":"NEMO","comment":"NEMO4D (MAMALAMA) : 31*15*30"},
{"group":"KIKO","comment":"#KIKOTOTO (MABURDUWUR) = 30*97"}
]