[
{"group":"ALLPAS","comment":"Tok99Toto ( AGDIK51 ) : 03*06*91"},
{"group":"BUKU","comment":"IYATOTO AGLEN77 31*04*68"},
{"group":"TIKTAK","comment":"Tiktaktogel / ALIEN35 / 38 , 32 , 53"},
{"group":"TAFSIR MIMPI","comment":"SIJITOGEL AGHER71 62*25*97"},
{"group":"KEI","comment":"#keitogel = (ALGA77) = 51*87*10"},
{"group":"LAHAN","comment":"#KIATOTO(ALASKA66)*07*72"},
{"group":"453P VIP","comment":"ASEPTOGEL AGDUL77 36*75*01"},
{"group":"UPIN","comment":"#UPINSLOT ( AGDA55 ) 45*94*71 BETTING"},
{"group":"PREDIKSI","comment":"MAJAPAHIT4D #ALTAR33 :: 03*06*91"},
{"group":"JNE","comment":"#JNETOTO(ALEMAN55)*31*04*68"},
{"group":"TOYIB","comment":"#TOYIBSLOT ( AGHIA53 ) : 38*32*53"},
{"group":"MASTER KUY","comment":"TOGELKUY AGFUD39 62*25*97"},
{"group":"KOI","comment":"#KOITOTO ( AGRIS79 ) 51*87"},
{"group":"K86","comment":"K86TOTO ( AGSAL55 ) : 07*72*96"},
{"group":"VESPA","comment":"VESPATOGEL (AGNIR57) 36*75*01"},
{"group":"NEMO","comment":"NEMO4D (ALBA44) : 45*94*71"},
{"group":"KIKO","comment":"#KIKOTOTO (ALAMBAKA58) = 81*67"}
]