[
{"group":"ALLPAS","comment":"Tok99Toto ( LILY64 ) : 46*17*61"},
{"group":"BUKU","comment":"IYATOTO LARON 38*05*65"},
{"group":"TIKTAK","comment":"Tiktaktogel / YUYUKANGKANG / 43 , 12 , 35"},
{"group":"TAFSIR MIMPI","comment":"SIJITOGEL MAWARHITAM 27*55*63"},
{"group":"KEI","comment":"#keitogel = (BABIHUTAN) = 13*89*76"},
{"group":"LAHAN","comment":"#KIATOTO(MAUNG545)*92*19"},
{"group":"453P VIP","comment":"ASEPTOGEL CACINGALASKA 88*01*44"},
{"group":"UPIN","comment":"#UPINSLOT ( KAKTUS ) 26*98*04 BETTING"},
{"group":"PREDIKSI","comment":"MAJAPAHIT4D #TULIP3 :: 82*47*37"},
{"group":"JNE","comment":"#JNETOTO(PITBULL)*72*94*93"},
{"group":"TOYIB","comment":"#TOYIBSLOT ( UBURUBUR2X ) : 00*42*90"},
{"group":"MASTER KUY","comment":"TOGELKUY SERIGALA 87*39*53"},
{"group":"KOI","comment":"#KOITOTO ( SERIGALAGALA ) 59*28"},
{"group":"K86","comment":"K86TOTO ( BUGENVIL ) : 56*45*29"},
{"group":"VESPA","comment":"VESPATOGEL (BELANAK) 81*64*52"},
{"group":"NEMO","comment":"NEMO4D (TREX) : 03*79*68"},
{"group":"KIKO","comment":"#KIKOTOTO (PIRANHAHAHA) = 75*08"}
]