[
{"group":"ALLPAS","comment":"Tok99Toto ( DINARCANDY ) : 85*28*15"},
{"group":"BUKU","comment":"IYATOTO ANISAMEI01 72*59*49"},
{"group":"TIKTAK","comment":"Tiktaktogel / ANANAN333 / 01 , 68 , 34"},
{"group":"TAFSIR MIMPI","comment":"SIJITOGEL ANAKU 92*98*17"},
{"group":"KEI","comment":"#keitogel = (ASIH123) = 13*58*88"},
{"group":"LAHAN","comment":"#KIATOTO(ANEH454)*80*67"},
{"group":"453P VIP","comment":"ASEPTOGEL ANJIRRR 03*43*87"},
{"group":"UPIN","comment":"#UPINSLOT ( DOGGYDOG ) 09*69*51 BETTING"},
{"group":"PULKAM","comment":"#PULKAMTOTO (DEWADEWI25) : 24*76*39"},
{"group":"JNE","comment":"#JNETOTO(ANISASA)*78*27*96"},
{"group":"TOYIB","comment":"#TOYIBSLOT ( AMEI04 ) : 84*04*14"},
{"group":"MASTER KUY","comment":"TOGELKUY ATIATI 02*36*20"},
{"group":"KOI","comment":"#KOITOTO ( ALELDUL88 ) 40*42"},
{"group":"K86","comment":"K86TOTO ( DUGEMXX ) : 95*29*75"},
{"group":"VESPA","comment":"VESPATOGEL (ANGRYBIRD) 89*32*91"},
{"group":"NEMO","comment":"NEMO4D (ANISAMEME) : 54*38*41"},
{"group":"KIKO","comment":"#KIKOTOTO (ARIARI37) = 50*33"}
]