[
{"group":"ALLPAS","comment":"Tok99Toto ( CUCOK ) : 68*52*55"},
{"group":"BUKU","comment":"IYATOTO FATFAT25 54*56*47"},
{"group":"TIKTAK","comment":"Tiktaktogel / FARMA03 / 16 , 50 , 34"},
{"group":"TAFSIR MIMPI","comment":"SIJITOGEL CEBOKIN 98*18*28"},
{"group":"KEI","comment":"#keitogel = (FANDOM) = 92*41*10"},
{"group":"LAHAN","comment":"#KIATOTO(FAKE123)*38*90"},
{"group":"453P VIP","comment":"ASEPTOGEL FOCUS 09*43*64"},
{"group":"UPIN","comment":"#UPINSLOT ( CIPOKDULU ) 03*46*05 BETTING"},
{"group":"PULKAM","comment":"#PULKAMTOTO (COMBRO22) : 94*81*66"},
{"group":"JNE","comment":"#JNETOTO(FASTRESP)*27*72*02"},
{"group":"TOYIB","comment":"#TOYIBSLOT ( FANBOY ) : 06*12*31"},
{"group":"MASTER KUY","comment":"TOGELKUY FAMUS 15*82*48"},
{"group":"KOI","comment":"#KOITOTO ( FORMUSA ) 86*73"},
{"group":"K86","comment":"K86TOTO ( CIWIS ) : 17*57*39"},
{"group":"VESPA","comment":"VESPATOGEL (FOLLOW) 23*83*65"},
{"group":"NEMO","comment":"NEMO4D (FANPAGE) : 99*42*29"},
{"group":"KIKO","comment":"#KIKOTOTO (FOURTWNTY) = 01*63"}
]