[
{"group":"ALLPAS","comment":"Tok99Toto ( DELOPONGBAE ) : 47*69*68"},
{"group":"BUKU","comment":"IYATOTO DELAKDELAK78 57*22*12"},
{"group":"TIKTAK","comment":"Tiktaktogel / DENGKIKU246 / 31 , 20 , 50"},
{"group":"TAFSIR MIMPI","comment":"SIJITOGEL DEMITSEGORO8 56*39*27"},
{"group":"KEI","comment":"#keitogel = (DENGAKSEKBOL) = 78*54*43"},
{"group":"LAHAN","comment":"#KIATOTO(DENGKULKOLOR)*34*03"},
{"group":"453P VIP","comment":"ASEPTOGEL DEMAKDEMEK58 62*14*28"},
{"group":"UPIN","comment":"#UPINSLOT ( DEDEGKATUL2 ) 75*17*65 BETTING"},
{"group":"PULKAM","comment":"#PULKAMTOTO (DELOSORBIB) : 02*30*38"},
{"group":"JNE","comment":"#JNETOTO(DEMIMIKAN71)*18*87*05"},
{"group":"TOYIB","comment":"#TOYIBSLOT ( DELOSORBIB ) : 13*80*05"},
{"group":"MASTER KUY","comment":"TOGELKUY DEMIKIANUDAH 21*92*36"},
{"group":"KOI","comment":"#KOITOTO ( DEDEGKATUL2 ) 01*73"},
{"group":"K86","comment":"K86TOTO ( DELAKDELAK78 ) : 63*76*19"},
{"group":"VESPA","comment":"VESPATOGEL (DEKDEKKAN96) 67*94*23"},
{"group":"NEMO","comment":"NEMO4D (DELEKEDELE20) : 88*64*51"},
{"group":"KIKO","comment":"#KIKOTOTO (DENDENGSAPI3) = 10*40"}
]