[
{"group":"ALLPAS","comment":"Tok99Toto ( DELOPONGBAE ) : 73*95*94"},
{"group":"BUKU","comment":"IYATOTO DELAKDELAK78 83*48*38"},
{"group":"TIKTAK","comment":"Tiktaktogel / DENGKIKU246 / 57 , 46 , 76"},
{"group":"TAFSIR MIMPI","comment":"SIJITOGEL DEMITSEGORO8 82*65*53"},
{"group":"KEI","comment":"#keitogel = (DENGAKSEKBOL) = 04*80*69"},
{"group":"LAHAN","comment":"#KIATOTO(DENGKULKOLOR)*60*29"},
{"group":"453P VIP","comment":"ASEPTOGEL DEMAKDEMEK58 88*40*54"},
{"group":"UPIN","comment":"#UPINSLOT ( DEDEGKATUL2 ) 01*43*91 BETTING"},
{"group":"PULKAM","comment":"#PULKAMTOTO (DELOSORBIB) : 28*56*64"},
{"group":"JNE","comment":"#JNETOTO(DEMIMIKAN71)*44*13*31"},
{"group":"TOYIB","comment":"#TOYIBSLOT ( DELOSORBIB ) : 39*06*31"},
{"group":"MASTER KUY","comment":"TOGELKUY DEMIKIANUDAH 47*18*62"},
{"group":"KOI","comment":"#KOITOTO ( DEDEGKATUL2 ) 27*99"},
{"group":"K86","comment":"K86TOTO ( DELAKDELAK78 ) : 89*02*45"},
{"group":"VESPA","comment":"VESPATOGEL (DEKDEKKAN96) 93*20*49"},
{"group":"NEMO","comment":"NEMO4D (DELEKEDELE20) : 14*90*77"},
{"group":"KIKO","comment":"#KIKOTOTO (DENDENGSAPI3) = 36*66"}
]