[
{"group":"ALTER","comment":"#ALTERTOTO#AMINTO15*30*92*53"},
{"group":"Hoho","comment":"AUMUR19 : 81*73*86 #HOHOTOGEL"},
{"group":"KAPAL","comment":"#KAPALSLOT ( AGAN28 ) = 02*21*98"},
{"group":"RIATOTO","comment":"#RIATOTO AMAR29 = 34*26*43"},
{"group":"PEDRO","comment":"#PEDRO4D (AMAR26*76*72*29)"},
{"group":"DIVA4D","comment":"#DIVA4D (KUMU17) = 13*69*05"},
{"group":"EYANG","comment":"#EYANGSLOT 45*03 ( AMIR25 )"},
{"group":"BLITAR","comment":"#BLITAR4D (AOQOM52) = 04*50"},
{"group":"LOGAM","comment":"#LOGAMTOTO=AOECK62= 20*91#"},
{"group":"TEST1","comment":"Leko"},
{"group":"TEST2","comment":"Nemo"},
{"group":"TEST3","comment":"Tiam"},
{"group":"TEST4","comment":"Telo"},
{"group":"TEST5","comment":"Bandu"},
{"group":"TEST6","comment":",Bafu"},
{"group":"TEST7","comment":"babus"},
{"group":"TEST8","comment":"Babu"}
]