[
{"group":"ALTER","comment":"#ALTERTOTO#INFORMASI*36*67*32"},
{"group":"Hoho","comment":"INTERAKSI : 19*74*41 #HOHOTOGEL"},
{"group":"KAPAL","comment":"#KAPALSLOT ( IMINGIMING ) = 55*18*56"},
{"group":"RIATOTO","comment":"#RIATOTO INGAT11 = 34*65*60"},
{"group":"PEDRO","comment":"#PEDRO4D (IKAT22*72*08*62)"},
{"group":"DIVA4D","comment":"#DIVA4D (INSPIRASI) = 14*69*85"},
{"group":"EYANG","comment":"#EYANGSLOT 22*33 ( INDUK33 )"},
{"group":"BLITAR","comment":"#BLITAR4D (IDEAL66) = 38*98"},
{"group":"LOGAM","comment":"#LOGAMTOTO=INTERAKSI1= 20*21#"},
{"group":"TEST1","comment":"Leko"},
{"group":"TEST2","comment":"Nemo"},
{"group":"TEST3","comment":"Tiam"},
{"group":"TEST4","comment":"Telo"},
{"group":"TEST5","comment":"Bandu"},
{"group":"TEST6","comment":",Bafu"},
{"group":"TEST7","comment":"babus"},
{"group":"TEST8","comment":"Babu"}
]