[
{"group":"ALTER","comment":"#ALTERTOTO#PANGGANG*37*80*89"},
{"group":"Hoho","comment":"PULPEN : 02*85*93 #HOHOTOGEL"},
{"group":"KAPAL","comment":"#KAPALSLOT ( PENGGARIS ) = 44*59*15"},
{"group":"RIATOTO","comment":"#RIATOTO PAYUNG3 = 49*69*90"},
{"group":"PEDRO","comment":"#PEDRO4D (PIRING2*00*39*23)"},
{"group":"DIVA4D","comment":"#DIVA4D (PINANG) = 29*32*05"},
{"group":"EYANG","comment":"#EYANGSLOT 35*83 ( PISANGG )"},
{"group":"BLITAR","comment":"#BLITAR4D (PANDANG) = 09*24"},
{"group":"LOGAM","comment":"#LOGAMTOTO=PETANI2= 12*28#"},
{"group":"TEST1","comment":"Leko"},
{"group":"TEST2","comment":"Nemo"},
{"group":"TEST3","comment":"Tiam"},
{"group":"TEST4","comment":"Telo"},
{"group":"TEST5","comment":"Bandu"},
{"group":"TEST6","comment":",Bafu"},
{"group":"TEST7","comment":"babus"},
{"group":"TEST8","comment":"Babu"}
]