[
{"group":"ALLPAS","comment":"Tok99Toto ( DEMIAPA ) : 73*75*05"},
{"group":"BUKU","comment":"IYATOTO DOAIBU1 90*69*35"},
{"group":"TIKTAK","comment":"Tiktaktogel / DURIHITAM / 76 , 71 , 11"},
{"group":"TAFSIR MIMPI","comment":"SIJITOGEL DOKARBALAP 13*26*41"},
{"group":"KEI","comment":"#keitogel = (DUKUPUNTANG) = 01*85*00"},
{"group":"LAHAN","comment":"#KIATOTO(DESAKU04)*07*98"},
{"group":"453P VIP","comment":"ASEPTOGEL DUYUNG45 21*09*14"},
{"group":"UPIN","comment":"#UPINSLOT ( DINASTI88 ) 56*64*66 BETTING"},
{"group":"PREDIKSI","comment":"MAJAPAHIT4D #DUDAMUDA04 :: 16*95*61"},
{"group":"JNE","comment":"#JNETOTO(DJANCUKMIN)*04*06*03"},
{"group":"TOYIB","comment":"#TOYIBSLOT ( DUNIAMAYA ) : 46*22*51"},
{"group":"MASTER KUY","comment":"TOGELKUY DEGRADASI 45*12*54"},
{"group":"KOI","comment":"#KOITOTO ( DRAWINGART ) 55*92"},
{"group":"K86","comment":"K86TOTO ( BLUR005 ) : 34*08*79"},
{"group":"VESPA","comment":"VESPATOGEL (DARMONO11) 86*58*63"},
{"group":"NEMO","comment":"NEMO4D (DIMSUM03) : 82*10*89"},
{"group":"KIKO","comment":"#KIKOTOTO (DUMPLING) = 52*27"}
]