[
{"group":"Hoho","comment":"TARON3 / TJDAL4 : 26*61*90 #HOHOTOGEL"},
{"group":"K86T","comment":"K86TOTO (TILOR1 ) : 12*18*54"},
{"group":"453P VIP","comment":"ASEPTOGEL TAVIX6 15*81*84"},
{"group":"Hatori","comment":"#HATORIBET*TIMAX9*34*73*85"},
{"group":"Dagelan","comment":"DAGELAN4D(TIMAX9) : 17*44*79"},
{"group":"DIVA4D","comment":"#DIVA4D (TOMEX2) = 03*35*98"},
{"group":"MASTER KUY","comment":"TOGELKUY TURAN8 57*86*97"},
{"group":"ALLPAS","comment":"Tok99Toto ( TIRON5 ) : 42*43*70"},
{"group":"TOYIB","comment":"#TOYIBSLOT ( TENOR7 ) : 12*18*54"},
{"group":"UPIN","comment":"#UPINSLOT ( TUPAX4) 34*73*85 BETTING"},
{"group":"VESPA","comment":"VESPATOGEL (TANUR7) 26*61*90"},
{"group":"OPUNG","comment":"OPUNG4D ( TIMAX9 ) : 42*43*70"},
{"group":"TAFSIR","comment":"SIJITOGEL TIVAX2 / TVDAK5 03*35*98"},
{"group":"BLITAR","comment":"#BLITAR4D (TIGRO1) = 57*86"},
{"group":"PEDRO","comment":"#PEDRO4D (TAVIX6*17*44*79)"},
{"group":"BUKU MIMPI","comment":"IYATOTO TULANG6 15*81*84"},
{"group":"","comment":""}
]