[
{"group":"ALTER","comment":"#ALTERTOTO#HISAP87*60*89*39"},
{"group":"Hoho","comment":"HEMBUS86 : 95*36*81 #HOHOTOGEL"},
{"group":"KAPAL","comment":"#KAPALSLOT ( HAMPA43 ) = 14*63*51"},
{"group":"RIATOTO","comment":"#RIATOTO HAMPIR45 = 69*54*74"},
{"group":"PEDRO","comment":"#PEDRO4D (HANGAT46*67*84*59)"},
{"group":"DIVA4D","comment":"#DIVA4D (HANGUS47) = 85*10*72"},
{"group":"EYANG","comment":"#EYANGSLOT 91*79 ( HEBAT48 )"},
{"group":"BLITAR","comment":"#BLITAR4D (HANDAL85) = 99*23"},
{"group":"LOGAM","comment":"#LOGAMTOTO=HUJAN82= 19*32#"},
{"group":"TEST1","comment":"Leko"},
{"group":"TEST2","comment":"Nemo"},
{"group":"TEST3","comment":"Tiam"},
{"group":"TEST4","comment":"Telo"},
{"group":"TEST5","comment":"Bandu"},
{"group":"TEST6","comment":",Bafu"},
{"group":"TEST7","comment":"babus"},
{"group":"TEST8","comment":"Babu"}
]